[{"index":"2007-11-01","seasonal":-1.7316,"trend":94.6399,"remainder":-3.0483},{"index":"2007-12-01","seasonal":0.5244,"trend":93.4341,"remainder":-2.6879},{"index":"2008-01-01","seasonal":5.0948,"trend":92.2282,"remainder":2.896},{"index":"2008-02-01","seasonal":13.1232,"trend":91.0223,"remainder":1.2745},{"index":"2008-03-01","seasonal":19.1276,"trend":89.7146,"remainder":3.6205},{"index":"2008-04-01","seasonal":-8.3058,"trend":88.407,"remainder":45.3574},{"index":"2008-05-01","seasonal":-4.3585,"trend":87.0993,"remainder":51.2749},{"index":"2008-06-01","seasonal":-6.2636,"trend":85.6324,"remainder":54.1158},{"index":"2008-07-01","seasonal":-4.5057,"trend":84.1655,"remainder":37.0283},{"index":"2008-08-01","seasonal":-7.3226,"trend":82.6986,"remainder":28.3879},{"index":"2008-09-01","seasonal":-4.0606,"trend":81.2062,"remainder":-0.4217},{"index":"2008-10-01","seasonal":0.4119,"trend":79.7139,"remainder":-22.6848},{"index":"2008-11-01","seasonal":-1.8432,"trend":78.2215,"remainder":-34.336},{"index":"2008-12-01","seasonal":0.3774,"trend":76.9417,"remainder":-35.3956},{"index":"2009-01-01","seasonal":4.1842,"trend":75.6618,"remainder":-40.5875},{"index":"2009-02-01","seasonal":11.1266,"trend":74.3819,"remainder":-37.4467},{"index":"2009-03-01","seasonal":16.2007,"trend":73.587,"remainder":-39.8381},{"index":"2009-04-01","seasonal":-6.537,"trend":72.7921,"remainder":-7.0426},{"index":"2009-05-01","seasonal":-3.3468,"trend":71.9972,"remainder":1.045},{"index":"2009-06-01","seasonal":-4.9191,"trend":72.6485,"remainder":-3.4362},{"index":"2009-07-01","seasonal":-3.7711,"trend":73.2997,"remainder":1.61},{"index":"2009-08-01","seasonal":-5.9675,"trend":73.9509,"remainder":1.4847},{"index":"2009-09-01","seasonal":-3.4943,"trend":74.4339,"remainder":4.8841},{"index":"2009-10-01","seasonal":-0.2896,"trend":74.9168,"remainder":3.5178},{"index":"2009-11-01","seasonal":-1.9479,"trend":75.3998,"remainder":1.1513},{"index":"2009-12-01","seasonal":0.2358,"trend":75.9252,"remainder":2.2416},{"index":"2010-01-01","seasonal":3.2773,"trend":76.4507,"remainder":-3.2754},{"index":"2010-02-01","seasonal":9.1325,"trend":76.9761,"remainder":-4.8187},{"index":"2010-03-01","seasonal":13.2751,"trend":77.6816,"remainder":-6.3815},{"index":"2010-04-01","seasonal":-4.7672,"trend":78.387,"remainder":0.4977},{"index":"2010-05-01","seasonal":-2.3344,"trend":79.0924,"remainder":-1.3535},{"index":"2010-06-01","seasonal":-3.5725,"trend":80.38,"remainder":-0.4247},{"index":"2010-07-01","seasonal":-3.033,"trend":81.6676,"remainder":-1.9678},{"index":"2010-08-01","seasonal":-4.6059,"trend":82.9552,"remainder":-2.8008},{"index":"2010-09-01","seasonal":-2.9184,"trend":84.7198,"remainder":0.1733},{"index":"2010-10-01","seasonal":-0.9774,"trend":86.4845,"remainder":-1.1923},{"index":"2010-11-01","seasonal":-2.0359,"trend":88.2491,"remainder":3.02},{"index":"2010-12-01","seasonal":0.0899,"trend":89.4918,"remainder":-0.0033},{"index":"2011-01-01","seasonal":2.4025,"trend":90.7346,"remainder":-3.394},{"index":"2011-02-01","seasonal":7.2179,"trend":91.9773,"remainder":3.786},{"index":"2011-03-01","seasonal":10.5272,"trend":92.8367,"remainder":6.6747},{"index":"2011-04-01","seasonal":-3.1414,"trend":93.696,"remainder":10.8021},{"index":"2011-05-01","seasonal":-1.3503,"trend":94.5553,"remainder":3.0836},{"index":"2011-06-01","seasonal":-2.4084,"trend":95.2019,"remainder":4.547},{"index":"2011-07-01","seasonal":-2.4453,"trend":95.8485,"remainder":-7.0624},{"index":"2011-08-01","seasonal":-3.4446,"trend":96.4951,"remainder":-7.4405},{"index":"2011-09-01","seasonal":-2.2898,"trend":96.461,"remainder":-7.7431},{"index":"2011-10-01","seasonal":-1.4729,"trend":96.4269,"remainder":2.2089},{"index":"2011-11-01","seasonal":-2.0964,"trend":96.3928,"remainder":4.2793},{"index":"2011-12-01","seasonal":-0.0334,"trend":96.2203,"remainder":4.1316},{"index":"2012-01-01","seasonal":1.5451,"trend":96.0478,"remainder":4.6696},{"index":"2012-02-01","seasonal":5.3149,"trend":95.8754,"remainder":5.0147},{"index":"2012-03-01","seasonal":7.785,"trend":95.591,"remainder":-0.03},{"index":"2012-04-01","seasonal":-1.5159,"trend":95.3067,"remainder":0.9251},{"index":"2012-05-01","seasonal":-0.3722,"trend":95.0223,"remainder":-12.2449},{"index":"2012-06-01","seasonal":-1.2551,"trend":94.423,"remainder":-5.2365},{"index":"2012-07-01","seasonal":-1.8732,"trend":93.8238,"remainder":2.2104},{"index":"2012-08-01","seasonal":-2.3023,"trend":93.2245,"remainder":3.6362},{"index":"2012-09-01","seasonal":-1.6832,"trend":93.0753,"remainder":-1.8212},{"index":"2012-10-01","seasonal":-1.992,"trend":92.9262,"remainder":-4.2018},{"index":"2012-11-01","seasonal":-2.2323,"trend":92.777,"remainder":-2.2992},{"index":"2012-12-01","seasonal":-0.2254,"trend":93.4638,"remainder":1.5902},{"index":"2013-01-01","seasonal":0.9398,"trend":94.1507,"remainder":0.2311},{"index":"2013-02-01","seasonal":3.6148,"trend":94.8375,"remainder":-5.4953},{"index":"2013-03-01","seasonal":5.3734,"trend":95.5286,"remainder":-8.8342},{"index":"2013-04-01","seasonal":-0.0282,"trend":96.2197,"remainder":-1.3919},{"index":"2013-05-01","seasonal":0.4113,"trend":96.9108,"remainder":-1.5215},{"index":"2013-06-01","seasonal":-0.2503,"trend":97.4833,"remainder":7.4656},{"index":"2013-07-01","seasonal":-1.329,"trend":98.0559,"remainder":9.8117},{"index":"2013-08-01","seasonal":-1.2111,"trend":98.6285,"remainder":8.8176},{"index":"2013-09-01","seasonal":-1.13,"trend":99.0983,"remainder":2.5843},{"index":"2013-10-01","seasonal":-2.447,"trend":99.5682,"remainder":-3.1897},{"index":"2013-11-01","seasonal":-2.3679,"trend":100.038,"remainder":0.2241},{"index":"2013-12-01","seasonal":-0.4208,"trend":99.639,"remainder":-4.3615},{"index":"2014-01-01","seasonal":0.3275,"trend":99.2399,"remainder":1.1078},{"index":"2014-02-01","seasonal":1.8997,"trend":98.8408,"remainder":-0.2315},{"index":"2014-03-01","seasonal":2.9386,"trend":97.4751,"remainder":1.6211},{"index":"2014-04-01","seasonal":1.4268,"trend":96.1093,"remainder":4.2587},{"index":"2014-05-01","seasonal":1.1527,"trend":94.7435,"remainder":9.2505},{"index":"2014-06-01","seasonal":0.7061,"trend":92.0411,"remainder":9.6446},{"index":"2014-07-01","seasonal":-0.8393,"trend":89.3387,"remainder":7.5768},{"index":"2014-08-01","seasonal":-0.1747,"trend":86.6363,"remainder":6.5727},{"index":"2014-09-01","seasonal":-0.6319,"trend":83.0619,"remainder":1.9091},{"index":"2014-10-01","seasonal":-2.9508,"trend":79.4875,"remainder":-0.7267},{"index":"2014-11-01","seasonal":-2.4291,"trend":75.9131,"remainder":-14.1944},{"index":"2014-12-01","seasonal":-0.4823,"trend":72.0939,"remainder":-24.2861},{"index":"2015-01-01","seasonal":0.0832,"trend":68.2748,"remainder":-17.6333},{"index":"2015-02-01","seasonal":1.0821,"trend":64.4557,"remainder":-17.6837},{"index":"2015-03-01","seasonal":2.3146,"trend":60.8607,"remainder":-8.5472},{"index":"2015-04-01","seasonal":1.8405,"trend":57.2656,"remainder":0.2658},{"index":"2015-05-01","seasonal":1.0305,"trend":53.6706,"remainder":5.1275},{"index":"2015-06-01","seasonal":0.7914,"trend":51.4043,"remainder":-1.2657},{"index":"2015-07-01","seasonal":-0.7761,"trend":49.1381,"remainder":-5.4729},{"index":"2015-08-01","seasonal":-0.0099,"trend":46.8718,"remainder":-1.3966},{"index":"2015-09-01","seasonal":-0.0252,"trend":45.7922,"remainder":0.5225},{"index":"2015-10-01","seasonal":-2.8427,"trend":44.7127,"remainder":1.0531},{"index":"2015-11-01","seasonal":-2.3946,"trend":43.6331,"remainder":-3.9113},{"index":"2015-12-01","seasonal":-0.4607,"trend":43.2897,"remainder":-11.0532},{"index":"2016-01-01","seasonal":-0.0905,"trend":42.9462,"remainder":-12.2392},{"index":"2016-02-01","seasonal":0.3178,"trend":42.6028,"remainder":-4.9597},{"index":"2016-03-01","seasonal":1.7266,"trend":43.0134,"remainder":-3.6153},{"index":"2016-04-01","seasonal":2.2727,"trend":43.424,"remainder":1.1},{"index":"2016-05-01","seasonal":0.9091,"trend":43.8346,"remainder":4.1095},{"index":"2016-06-01","seasonal":0.8661,"trend":44.8611,"remainder":-0.9277},{"index":"2016-07-01","seasonal":-0.7347,"trend":45.8875,"remainder":-0.3537},{"index":"2016-08-01","seasonal":0.132,"trend":46.914,"remainder":-1.8203},{"index":"2016-09-01","seasonal":0.5575,"trend":47.4987,"remainder":1.8838},{"index":"2016-10-01","seasonal":-2.7501,"trend":48.0834,"remainder":0.4309},{"index":"2016-11-01","seasonal":-2.1506,"trend":48.6681,"remainder":5.6482},{"index":"2016-12-01","seasonal":-0.3258,"trend":48.8964,"remainder":4.0379},{"index":"2017-01-01","seasonal":-0.0916,"trend":49.1247,"remainder":4.4289},{"index":"2017-02-01","seasonal":0.28,"trend":49.353,"remainder":0.0409},{"index":"2017-03-01","seasonal":1.6135,"trend":49.8494,"remainder":-0.3456},{"index":"2017-04-01","seasonal":2.3505,"trend":50.3458,"remainder":-4.1568},{"index":"2017-05-01","seasonal":0.5961,"trend":50.8422,"remainder":-6.2424},{"index":"2017-06-01","seasonal":0.634,"trend":51.7194,"remainder":-5.6784},{"index":"2017-07-01","seasonal":-1.2989,"trend":52.5966,"remainder":-3.2399},{"index":"2017-08-01","seasonal":-0.6276,"trend":53.4738,"remainder":-2.9692},{"index":"2017-09-01","seasonal":1.2992,"trend":54.9296,"remainder":-4.6342},{"index":"2017-10-01","seasonal":-2.5884,"trend":56.3854,"remainder":2.8659},{"index":"2017-11-01","seasonal":-1.786,"trend":57.8412,"remainder":1.8918},{"index":"2017-12-01","seasonal":-0.0832,"trend":59.5098,"remainder":4.2325},{"index":"2018-01-01","seasonal":0.0022,"trend":61.1784,"remainder":1.0031},{"index":"2018-02-01","seasonal":0.3203,"trend":62.8469,"remainder":-0.3953},{"index":"2018-03-01","seasonal":1.5618,"trend":63.475,"remainder":1.2885},{"index":"2018-04-01","seasonal":2.4724,"trend":64.103,"remainder":3.4078},{"index":"2018-05-01","seasonal":0.3098,"trend":64.731,"remainder":2.282},{"index":"2018-06-01","seasonal":0.4139,"trend":64.277,"remainder":5.8911},{"index":"2018-07-01","seasonal":-1.8655,"trend":63.8229,"remainder":5.8879},{"index":"2018-08-01","seasonal":-1.3991,"trend":63.3688,"remainder":8.115},{"index":"2018-09-01","seasonal":2.0195,"trend":62.6978,"remainder":6.0405},{"index":"2018-10-01","seasonal":-2.4522,"trend":62.0267,"remainder":-2.8812},{"index":"2018-11-01","seasonal":-1.3596,"trend":61.3557,"remainder":-11.0131},{"index":"2018-12-01","seasonal":0.2305,"trend":60.4287,"remainder":-9.1087},{"index":"2019-01-01","seasonal":0.1528,"trend":59.5017,"remainder":-4.674},{"index":"2019-02-01","seasonal":0.516,"trend":58.5747,"remainder":-0.9226},{"index":"2019-03-01","seasonal":1.6839,"trend":58.0814,"remainder":4.1057},{"index":"2019-04-01","seasonal":2.5498,"trend":57.588,"remainder":0.7276},{"index":"2019-05-01","seasonal":-0.1474,"trend":57.0947,"remainder":-2.2407},{"index":"2019-06-01","seasonal":0.1654,"trend":56.9866,"remainder":0.3945},{"index":"2019-07-01","seasonal":-2.4689,"trend":56.8784,"remainder":0.4345},{"index":"2019-08-01","seasonal":-2.233,"trend":56.7703,"remainder":2.4297},{"index":"2019-09-01","seasonal":2.7091,"trend":55.7957,"remainder":-4.4992},{"index":"2019-10-01","seasonal":-2.3179,"trend":54.821,"remainder":4.5669},{"index":"2019-11-01","seasonal":-0.9317,"trend":53.8464,"remainder":6.8901},{"index":"2019-12-01","seasonal":0.546,"trend":52.5741,"remainder":4.4085},{"index":"2020-01-01","seasonal":0.3056,"trend":51.3018,"remainder":-1.0653},{"index":"2020-02-01","seasonal":0.7126,"trend":50.0295,"remainder":-20.2966},{"index":"2020-03-01","seasonal":1.8055,"trend":49.0955,"remainder":-34.2019},{"index":"2020-04-01","seasonal":2.6241,"trend":48.1615,"remainder":-22.2582},{"index":"2020-05-01","seasonal":-0.6103,"trend":47.2276,"remainder":-8.3036},{"index":"2020-06-01","seasonal":-0.0914,"trend":46.6991,"remainder":-5.8418},{"index":"2020-07-01","seasonal":-3.0831,"trend":46.1707,"remainder":-0.6995},{"index":"2020-08-01","seasonal":-3.0798,"trend":45.6422,"remainder":-2.9367},{"index":"2020-09-01","seasonal":3.3841,"trend":47.3312,"remainder":-11.1607},{"index":"2020-10-01","seasonal":-2.1991,"trend":49.0202,"remainder":-5.4746},{"index":"2020-11-01","seasonal":-0.4723,"trend":50.7092,"remainder":-3.1687},{"index":"2020-12-01","seasonal":0.8916,"trend":53.5677,"remainder":-2.3572},{"index":"2021-01-01","seasonal":0.4999,"trend":56.4262,"remainder":2.135},{"index":"2021-02-01","seasonal":1.0397,"trend":59.2847,"remainder":2.033},{"index":"2021-03-01","seasonal":2.0156,"trend":62.2763,"remainder":-2.5881},{"index":"2021-04-01","seasonal":2.6591,"trend":65.2679,"remainder":-2.7699},{"index":"2021-05-01","seasonal":-1.1705,"trend":68.2595,"remainder":4.2637},{"index":"2021-06-01","seasonal":-0.3679,"trend":71.3144,"remainder":1.484},{"index":"2021-07-01","seasonal":-3.7207,"trend":74.3692,"remainder":-2.9372},{"index":"2021-08-01","seasonal":-3.9885,"trend":77.4241,"remainder":-3.3123},{"index":"2021-09-01","seasonal":4.0176,"trend":80.5057,"remainder":5.3367}]
